testpoetry2/__init__.py
testpoetry2/__main__.py
testpoetry2/__version__.py
testpoetry2/console/__init__.py
testpoetry2/console/application.py
testpoetry2/pwgen.py
testpoetry2/test/__init__.py
testpoetry2/test/__main__.py
testpoetry2/test/pattern-list-error.txt
testpoetry2/test/pattern-list.txt
testpoetry2/test/pwgen_test.py
testpoetry2-0.1.17.dist-info/entry_points.txt
testpoetry2-0.1.17.dist-info/METADATA
testpoetry2-0.1.17.dist-info/WHEEL
testpoetry2-0.1.17.dist-info/RECORD
