Metadata-Version: 2.1
Name: testpoetry2
Version: 0.1.17
Summary: Password generator CLI and library
Author: Bill.Avramenko
Author-email: billavramenko@gmail.com
Requires-Python: >=3.10,<4.0
Classifier: Programming Language :: Python :: 3
Classifier: Programming Language :: Python :: 3.10
Classifier: Programming Language :: Python :: 3.11
Requires-Dist: questionary (>=1.10.0,<2.0.0)
